psi/__init__.py
psi/psi.py
psi/assets/app.desktop
psi/assets/installer.nsi
psi/assets/snapcraft.yaml
psi/subcmds/__init__.py
psi/subcmds/build.py
psi/subcmds/create.py
psi/subcmds/precache.py
psi/subcmds/run.py
psi/utils/__init__.py
psi/utils/build_dmg.py
psi/utils/build_mac.py
psi/utils/build_nsis.py
psi/utils/build_snap.py
psi/utils/download.py
psi_cli-0.0.4.dist-info/LICENSE
psi_cli-0.0.4.dist-info/METADATA
psi_cli-0.0.4.dist-info/WHEEL
psi_cli-0.0.4.dist-info/entry_points.txt
psi_cli-0.0.4.dist-info/top_level.txt
psi_cli-0.0.4.dist-info/RECORD
