Metadata-Version: 2.1
Name: psi-cli
Version: 0.0.4
Summary: flutter-rs devtool
Home-page: https://github.com/flutter-rs/psi-cli
Author: juju
Author-email: gliheng@live.com
License: MIT
Platform: UNKNOWN
Classifier: Programming Language :: Python :: 3
Classifier: License :: OSI Approved :: MIT License
Classifier: Operating System :: OS Independent
Requires-Python: >=3.0
Requires-Dist: toml (==0.10.0)
Requires-Dist: dmgbuild (==1.3.2)
Requires-Dist: requests (==2.22.0)
